{"chunk_definitions":[{"row":34,"row_count":1,"visible":true,"expansion_state":0,"options":{"engine":"r","label":"unnamed-chunk-171"},"document_id":"6B3A846F","chunk_id":"cwn529y3cv09o","chunk_label":"unnamed-chunk-1"},{"row":289,"row_count":1,"visible":true,"expansion_state":0,"options":{"engine":"r","label":"unnamed-chunk-170"},"document_id":"6B3A846F","chunk_id":"camc6syp2fpoo","chunk_label":"unnamed-chunk-28"},{"row":372,"row_count":1,"visible":true,"expansion_state":0,"options":{"engine":"r","label":"unnamed-chunk-173"},"document_id":"6B3A846F","chunk_id":"cv0v7exu8cej7","chunk_label":"unnamed-chunk-34"},{"row":391,"row_count":1,"visible":true,"expansion_state":0,"options":{"engine":"r","label":"unnamed-chunk-192"},"document_id":"6B3A846F","chunk_id":"c67wqbdf08g7n","chunk_label":"unnamed-chunk-35"},{"row":397,"row_count":1,"visible":true,"expansion_state":0,"options":{"engine":"r","label":"unnamed-chunk-198"},"document_id":"6B3A846F","chunk_id":"cph28mq3fuqhw","chunk_label":"unnamed-chunk-36"}],"doc_write_time":1687439432}